odoo/addons/fieldservice/README.rst
odoo/addons/fieldservice/__init__.py
odoo/addons/fieldservice/__manifest__.py
odoo/addons/fieldservice/data/fsm_stage.xml
odoo/addons/fieldservice/data/fsm_team.xml
odoo/addons/fieldservice/data/ir_sequence.xml
odoo/addons/fieldservice/data/mail_message_subtype.xml
odoo/addons/fieldservice/data/module_category.xml
odoo/addons/fieldservice/models/__init__.py
odoo/addons/fieldservice/models/fsm_branch.py
odoo/addons/fieldservice/models/fsm_category.py
odoo/addons/fieldservice/models/fsm_district.py
odoo/addons/fieldservice/models/fsm_equipment.py
odoo/addons/fieldservice/models/fsm_location.py
odoo/addons/fieldservice/models/fsm_order.py
odoo/addons/fieldservice/models/fsm_person.py
odoo/addons/fieldservice/models/fsm_region.py
odoo/addons/fieldservice/models/fsm_route.py
odoo/addons/fieldservice/models/fsm_stage.py
odoo/addons/fieldservice/models/fsm_tag.py
odoo/addons/fieldservice/models/fsm_team.py
odoo/addons/fieldservice/models/fsm_template.py
odoo/addons/fieldservice/models/fsm_territory.py
odoo/addons/fieldservice/models/res_config_settings.py
odoo/addons/fieldservice/models/res_country.py
odoo/addons/fieldservice/models/res_partner.py
odoo/addons/fieldservice/models/res_state.py
odoo/addons/fieldservice/readme/CONFIGURE.rst
odoo/addons/fieldservice/readme/CONTRIBUTORS.rst
odoo/addons/fieldservice/readme/CREDITS.rst
odoo/addons/fieldservice/readme/DESCRIPTION.rst
odoo/addons/fieldservice/readme/INSTALL.rst
odoo/addons/fieldservice/readme/ROADMAP.rst
odoo/addons/fieldservice/readme/USAGE.rst
odoo/addons/fieldservice/security/ir.model.access.csv
odoo/addons/fieldservice/security/res_groups.xml
odoo/addons/fieldservice/static/description/icon.png
odoo/addons/fieldservice/static/description/index.html
odoo/addons/fieldservice/static/src/js/fsm_gantt.js
odoo/addons/fieldservice/static/src/js/fsm_gantt_person_filter.js
odoo/addons/fieldservice/static/src/less/fsm_gantt_person_filter.less
odoo11_addon_fieldservice-11.0.0.2.0.dist-info/METADATA
odoo11_addon_fieldservice-11.0.0.2.0.dist-info/RECORD
odoo11_addon_fieldservice-11.0.0.2.0.dist-info/WHEEL
odoo11_addon_fieldservice-11.0.0.2.0.dist-info/top_level.txt
